{"backend_name": "ibmq_quito", "backend_version": "1.1.45", "date": "2023-09-08T01:57:14+02:00", "header": {"backend_name": "ibmq_quito", "backend_version": "1.1.45", "_ibm_tracing_": {"uber-trace-id": "21b35847651e90a7b3e9ca946e8901be:e92138b094cc389d:0000000000000000:03", "uberctx-job_id": "cjt66gkbhllfakijt1jg"}}, "qobj_id": "5443437b-ccbb-4f88-8be5-8840dffcf581", "job_id": "circuit-runner_cjt66gkbhllfakijt1jg_6a0f_0", "status": "Successful completion", "success": true, "results": [{"shots": 16000, "success": true, "data": {"counts": {"0x0": 1392, "0x1": 851, "0x10": 808, "0x11": 666, "0x12": 822, "0x13": 901, "0x14": 678, "0x15": 634, "0x16": 615, "0x17": 499, "0x18": 275, "0x19": 257, "0x1a": 272, "0x1b": 261, "0x1c": 287, "0x1d": 267, "0x1e": 224, "0x1f": 261, "0x2": 677, "0x3": 615, "0x4": 681, "0x5": 764, "0x6": 610, "0x7": 594, "0x8": 344, "0x9": 304, "0xa": 277, "0xb": 219, "0xc": 237, "0xd": 257, "0xe": 236, "0xf": 215}}, "meas_level": 2, "header": {"qubit_labels": [["q", 0], ["q", 1], ["q", 2], ["q", 3], ["q", 4]], "n_qubits": 5, "qreg_sizes": [["q", 5]], "clbit_labels": [["meas", 0], ["meas", 1], ["meas", 2], ["meas", 3], ["meas", 4]], "memory_slots": 5, "creg_sizes": [["meas", 5]], "name": "ibm_synth_1", "global_phase": 3.1415926535897936, "metadata": {}}, "status": "done"}], "execution_id": "3ffcd2a6-4dda-11ee-bb63-b02628f7f59e", "time_taken": 5.513987937, "error": null}