{"backend_name": "ibmq_quito", "backend_version": "1.1.42", "date": "2023-07-16T12:29:58+02:00", "header": {"backend_name": "ibmq_quito", "backend_version": "1.1.42", "_ibm_tracing_": {"uber-trace-id": "ec3aa2c5ec680931336fd59d13f6a7b6:29221a07c079094f:300bad8ef6031445:1"}}, "qobj_id": "78dcd675-cc23-4d50-b320-6e32cd541705", "job_id": "circuit-runner_cipsd5j6iebd0dncp990_7790_0", "status": "Successful completion", "success": true, "results": [{"shots": 8000, "success": true, "data": {"counts": {"0x0": 63, "0x1": 157, "0x10": 62, "0x11": 193, "0x12": 154, "0x13": 683, "0x14": 126, "0x15": 562, "0x16": 82, "0x17": 295, "0x18": 92, "0x19": 215, "0x1a": 146, "0x1b": 582, "0x1c": 183, "0x1d": 653, "0x1e": 65, "0x1f": 217, "0x2": 94, "0x3": 394, "0x4": 150, "0x5": 542, "0x6": 75, "0x7": 244, "0x8": 89, "0x9": 195, "0xa": 130, "0xb": 499, "0xc": 152, "0xd": 571, "0xe": 81, "0xf": 254}}, "meas_level": 2, "header": {"clbit_labels": [["meas", 0], ["meas", 1], ["meas", 2], ["meas", 3], ["meas", 4]], "creg_sizes": [["meas", 5]], "global_phase": 4.71238898038469, "memory_slots": 5, "metadata": {}, "n_qubits": 5, "name": "clifford_synth_13", "qreg_sizes": [["q", 5]], "qubit_labels": [["q", 0], ["q", 1], ["q", 2], ["q", 3], ["q", 4]]}, "status": "done"}], "execution_id": "b3983016-23c3-11ee-b2c1-b02628f7f59e", "time_taken": 4.974388187, "error": null, "client_version": {"qiskit": "0.39.0"}}