{"backend_name": "ibmq_quito", "backend_version": "1.1.42", "date": "2023-07-16T12:29:52+02:00", "header": {"backend_name": "ibmq_quito", "backend_version": "1.1.42", "_ibm_tracing_": {"uber-trace-id": "8663ce7eaf4b18dc475cd4cd0b1cbbbc:c910baf6d154867d:1ae3e4b3364a8aee:1"}}, "qobj_id": "22d9d811-5165-4be6-93b2-bbf30311c27a", "job_id": "circuit-runner_cipsd4acdfacvk4pa9p0_c9c9_0", "status": "Successful completion", "success": true, "results": [{"shots": 8000, "success": true, "data": {"counts": {"0x0": 807, "0x1": 435, "0x10": 171, "0x11": 142, "0x12": 191, "0x13": 100, "0x14": 63, "0x15": 173, "0x16": 135, "0x17": 115, "0x18": 120, "0x19": 255, "0x1a": 94, "0x1b": 106, "0x1c": 157, "0x1d": 107, "0x1e": 169, "0x1f": 133, "0x2": 54, "0x3": 55, "0x4": 335, "0x5": 1045, "0x6": 38, "0x7": 54, "0x8": 426, "0x9": 919, "0xa": 35, "0xb": 61, "0xc": 1031, "0xd": 383, "0xe": 56, "0xf": 35}}, "meas_level": 2, "header": {"clbit_labels": [["meas", 0], ["meas", 1], ["meas", 2], ["meas", 3], ["meas", 4]], "creg_sizes": [["meas", 5]], "global_phase": 2.356194490192344, "memory_slots": 5, "metadata": {}, "n_qubits": 5, "name": "Clifford: Stabilizer = ['+IZZIZ', '-ZYIIY', '+IZZZZ', '+IXXIZ', '+ZIIZI'], Destabilizer = ['+YYXXX', '-IYYIZ', '+XXXXI', '-ZYZZY', '+XIIIZ']", "qreg_sizes": [["q", 5]], "qubit_labels": [["q", 0], ["q", 1], ["q", 2], ["q", 3], ["q", 4]]}, "status": "done"}], "execution_id": "b035e21a-23c3-11ee-b2c1-b02628f7f59e", "time_taken": 4.9943270129999995, "error": null, "client_version": {"qiskit": "0.39.0"}}